anurbs.cp39-win_amd64.pyd
anurbs-0.15.0.dist-info/LICENSE
anurbs-0.15.0.dist-info/METADATA
anurbs-0.15.0.dist-info/WHEEL
anurbs-0.15.0.dist-info/top_level.txt
anurbs-0.15.0.dist-info/RECORD
