Metadata-Version: 2.1
Name: anurbs
Version: 0.15.0
Summary: A simple Nurbs library
Home-page: https://github.com/oberbichler/ANurbs
Author: Thomas Oberbichler
Author-email: thomas.oberbichler@gmail.com
License: UNKNOWN
Platform: UNKNOWN
License-File: LICENSE
Requires-Dist: msvc-runtime ; platform_system == "Windows"
